hello_world_omnaik/__init__.py
hello_world_omnaik-1.1.2.dist-info/METADATA
hello_world_omnaik-1.1.2.dist-info/WHEEL
hello_world_omnaik-1.1.2.dist-info/top_level.txt
hello_world_omnaik-1.1.2.dist-info/RECORD
