Metadata-Version: 2.4
Name: hello-world-omnaik
Version: 1.1.2
Summary: Add your description here
Requires-Python: >=3.14
Requires-Dist: flask>=3.1.2
Requires-Dist: requests==2.31.0
